triangle/tri.py
triangle/__init__.py
triangle/data.py
triangle/plot.py
triangle/version.py
triangle/core.cpython-310-i386-linux-gnu.so
triangle/data/spiral.node
triangle/data/box.2.ele
triangle/data/A.1.ele
triangle/data/double_hex.poly
triangle/data/double_hex3.1.node
triangle/data/la.1.node
triangle/data/box.1.ele
triangle/data/diamond_02_00009.node
triangle/data/la.poly
triangle/data/double_hex3.1.poly
triangle/data/ell.ele
triangle/data/bbox.1.node
triangle/data/greenland.node
triangle/data/double_hex.2.poly
triangle/data/spiral.1.ele
triangle/data/double_hex.1.poly
triangle/data/face.1.node
triangle/data/double_hex3.1.ele
triangle/data/box.1.node
triangle/data/double_hex2.2.ele
triangle/data/diamond_02_00009.1.v.node
triangle/data/box.3.node
triangle/data/spiral.q.1.node
triangle/data/box.4.ele
triangle/data/double_hex2.poly
triangle/data/double_hex2.1.ele
triangle/data/box.3.poly
triangle/data/double_hex.1.ele
triangle/data/dots.1.v.node
triangle/data/bbox.1.area
triangle/data/double_hex.2.ele
triangle/data/la.1.poly
triangle/data/face.poly
triangle/data/diamond_02_00009.1.node
triangle/data/double_hex.1.node
triangle/data/bbox.1.ele
triangle/data/dots.1.v.edge
triangle/data/double_hex3.node
triangle/data/box.4.node
triangle/data/la.1.ele
triangle/data/spiral.r.1.ele
triangle/data/A.1.node
triangle/data/double_hex2.2.poly
triangle/data/square_circle_hole.1.node
triangle/data/double_hex3.poly
triangle/data/face.1.ele
triangle/data/spiral.q.1.ele
triangle/data/box.4.poly
triangle/data/box.poly
triangle/data/box.3.ele
triangle/data/box.2.node
triangle/data/greenland.ele
triangle/data/dots.node
triangle/data/spiral.r.1.node
triangle/data/double_hex2.1.node
triangle/data/spiral.1.node
triangle/data/double_hex2.1.poly
triangle/data/A.1.poly
triangle/data/face.1.poly
triangle/data/double_hex.2.node
triangle/data/box.2.poly
triangle/data/double_hex2.2.node
triangle/data/ell.node
triangle-20250106.dist-info/METADATA
triangle-20250106.dist-info/RECORD
triangle-20250106.dist-info/top_level.txt
triangle-20250106.dist-info/WHEEL
triangle-20250106.dist-info/LICENSE
